py_package_test/__init__.py
py_package_test/add.py
py_package_test/sub.py
py_package_test/extras/__init__.py
py_package_test/extras/divide.py
py_package_test/extras/multiply.py
py_package_test-0.0.3.dist-info/METADATA
py_package_test-0.0.3.dist-info/WHEEL
py_package_test-0.0.3.dist-info/top_level.txt
py_package_test-0.0.3.dist-info/RECORD
