Metadata-Version: 2.1
Name: py-package-test
Version: 0.0.3
Summary: Py package test
Author: Sanjay
Author-email: youremail@email.com
Keywords: python,first package
Classifier: Development Status :: 3 - Alpha
Classifier: Intended Audience :: Education
Classifier: Programming Language :: Python :: 2
Classifier: Programming Language :: Python :: 3
Classifier: Operating System :: MacOS :: MacOS X
Classifier: Operating System :: Microsoft :: Windows
